README.txt
Tmfiles.py
setup.py
Tmfiles.egg-info/PKG-INFO
Tmfiles.egg-info/SOURCES.txt
Tmfiles.egg-info/dependency_links.txt
Tmfiles.egg-info/top_level.txt