Metadata-Version: 2.1
Name: Tmfiles
Version: 0.1
Summary: Files Treat
Home-page: UNKNOWN
Author: Dr.tamer
Author-email: tmrbe2006@Gmail.com
License: UNKNOWN
Keywords: Files
Platform: UNKNOWN
Classifier: Programming Language :: Python :: 3
Classifier: License :: OSI Approved :: MIT License
Classifier: Operating System :: OS Independent
